availability/__init__.py
availability/admin.py
availability/apps.py
availability/conf.py
availability/models.py
availability/selectors.py
availability/migrations/0001_initial.py
availability/migrations/__init__.py
django_availability-0.1.0.dist-info/licenses/LICENSE
django_availability-0.1.0.dist-info/METADATA
django_availability-0.1.0.dist-info/WHEEL
django_availability-0.1.0.dist-info/top_level.txt
django_availability-0.1.0.dist-info/RECORD
