Metadata-Version: 2.4
Name: django-availability
Version: 0.1.0
Summary: Reusable availability modelling for Django providers/resources.
Author: Kevin Oudai
License: MIT License
Project-URL: Homepage, https://github.com/mroudai/django-availability
Keywords: django,availability,scheduling,booking
Classifier: Framework :: Django
Classifier: Framework :: Django :: 4.2
Classifier: Framework :: Django :: 5.0
Classifier: License :: OSI Approved :: MIT License
Classifier: Programming Language :: Python :: 3
Classifier: Programming Language :: Python :: 3 :: Only
Classifier: Programming Language :: Python :: 3.10
Classifier: Programming Language :: Python :: 3.11
Classifier: Programming Language :: Python :: 3.12
Classifier: Programming Language :: Python :: 3.13
Classifier: Intended Audience :: Developers
Classifier: Topic :: Software Development :: Libraries :: Python Modules
Requires-Python: >=3.10
License-File: LICENSE
Requires-Dist: Django>=4.2
Dynamic: license-file
